deploy_time_build/__init__.py
deploy_time_build/py.typed
deploy_time_build/_jsii/__init__.py
deploy_time_build/_jsii/deploy-time-build@0.4.5.jsii.tgz
deploy_time_build-0.4.5.dist-info/LICENSE
deploy_time_build-0.4.5.dist-info/METADATA
deploy_time_build-0.4.5.dist-info/WHEEL
deploy_time_build-0.4.5.dist-info/top_level.txt
deploy_time_build-0.4.5.dist-info/RECORD
